examples/API/test_api.py
examples/custom/txt/custom_input.py
ftio/__init__.py
ftio/__main__.py
ftio/api/gekkoFs/__init__.py
ftio/api/gekkoFs/ftio_gekko.py
ftio/api/gekkoFs/parse_gekko.py
ftio/api/gekkoFs/predictor_gekko.py
ftio/api/gekkoFs/predictor_gekko_zmq.py
ftio/api/gekkoFs/stage_data.py
ftio/api/gekkoFs/jit/__init__.py
ftio/api/gekkoFs/jit/execute_and_wait.py
ftio/api/gekkoFs/jit/jit.py
ftio/api/gekkoFs/jit/jit_plot.py
ftio/api/gekkoFs/jit/jitsettings.py
ftio/api/gekkoFs/jit/jittime.py
ftio/api/gekkoFs/jit/setup_check.py
ftio/api/gekkoFs/jit/setup_core.py
ftio/api/gekkoFs/jit/setup_helper.py
ftio/api/gekkoFs/jit/setup_init.py
ftio/api/metric_proxy/helper.py
ftio/api/metric_proxy/parallel_proxy.py
ftio/api/metric_proxy/parse_proxy.py
ftio/api/metric_proxy/phasemode.py
ftio/api/metric_proxy/plot_proxy.py
ftio/api/metric_proxy/proxy.py
ftio/api/metric_proxy/proxy_analysis.py
ftio/api/metric_proxy/proxy_cluster.py
ftio/api/metric_proxy/proxy_invoke_ftio.py
ftio/api/metric_proxy/req.py
ftio/api/trace_analysis/helper.py
ftio/api/trace_analysis/parallel_trace_analysis.py
ftio/api/trace_analysis/plot_csv.py
ftio/api/trace_analysis/trace_analysis.py
ftio/api/trace_analysis/trace_ftio.py
ftio/api/trace_analysis/trace_ftio_v2.py
ftio/cli/__init__.py
ftio/cli/ftio_core.py
ftio/cli/predictor.py
ftio/freq/__init__.py
ftio/freq/_dft.py
ftio/freq/_wavelet.py
ftio/freq/anomaly_detection.py
ftio/freq/autocorrelation.py
ftio/freq/discretize.py
ftio/freq/dtw.py
ftio/freq/freq_data.py
ftio/freq/freq_html.py
ftio/freq/helper.py
ftio/freq/perodicity_detection.py
ftio/freq/time_window.py
ftio/parse/__init__.py
ftio/parse/args.py
ftio/parse/bandwidth.py
ftio/parse/csv_reader.py
ftio/parse/custom_patterns.py
ftio/parse/darshan_reader.py
ftio/parse/extract.py
ftio/parse/ftio_to_extrap.py
ftio/parse/helper.py
ftio/parse/input_template.py
ftio/parse/metrics.py
ftio/parse/msgpack_reader.py
ftio/parse/overlap_thread.py
ftio/parse/parse_custom.py
ftio/parse/parse_darshan.py
ftio_hpc-0.0.6.dist-info/LICENSE
ftio_hpc-0.0.6.dist-info/METADATA
ftio_hpc-0.0.6.dist-info/WHEEL
ftio_hpc-0.0.6.dist-info/entry_points.txt
ftio_hpc-0.0.6.dist-info/top_level.txt
ftio_hpc-0.0.6.dist-info/RECORD
