Metadata-Version: 2.2
Name: ftio-hpc
Version: 0.0.6
Summary: Frequency Techniques for I/O
Author-email: Ahmad Tarraf <ahmad.tarraf@tu-darmstadt.de>
Maintainer-email: Ahmad Tarraf <ahmad.tarraf@tu-darmstadt.de>
License: BSD 3-Clause License
Project-URL: Homepage, https://github.com/tuda-parallel/FTIO
Project-URL: Documentation, https://github.com/tuda-parallel/FTIO/docs
Project-URL: Repository, https://github.com/tuda-parallel/FTIO
Project-URL: Bug Tracker, https://github.com/tuda-parallel/FTIO/issues
Project-URL: Changelog, https://github.com/tuda-parallel/FTIO/blob/master/CHANGELOG.md
Keywords: ftio,I/O
Classifier: Development Status :: 5 - Production/Stable
Classifier: License :: OSI Approved :: BSD License
Classifier: Operating System :: OS Independent
Classifier: Programming Language :: Python :: 3
Classifier: Programming Language :: Python :: 3 :: Only
Classifier: Programming Language :: Python :: 3.8
Classifier: Programming Language :: Python :: 3.9
Classifier: Programming Language :: Python :: 3.10
Classifier: Programming Language :: Python :: 3.11
Classifier: Programming Language :: Python :: 3.12
Classifier: Programming Language :: Python :: 3.13
Classifier: Operating System :: OS Independent
Classifier: Intended Audience :: Developers
Classifier: Intended Audience :: Science/Research
Classifier: Topic :: Scientific/Engineering
Classifier: Topic :: Software Development
Classifier: Topic :: Software Development :: Libraries :: Python Modules
Requires-Python: >=3.8
License-File: LICENSE
Requires-Dist: scikit-learn
Requires-Dist: pyzmq
Requires-Dist: numba
Requires-Dist: darshan
Requires-Dist: fastdtw
Requires-Dist: scipy
Requires-Dist: pandas
Requires-Dist: jsonlines
Requires-Dist: plotly
Requires-Dist: dash
Requires-Dist: kneed
Requires-Dist: PyWavelets
Requires-Dist: trace_updater
Requires-Dist: plotly_resampler
Requires-Dist: msgpack
Requires-Dist: rich
Requires-Dist: dash_extensions
Requires-Dist: pytest
Requires-Dist: fastcluster
Provides-Extra: debug
